{
  "$schema": "http://json-schema.org/draft-04/schema#",
  "description": "Record of an e-book",
  "type": "object",
  "properties": {
    "bookdata": {
      "type": "object",
      "properties": {
        "id": {
          "description": "Unique ID (UUID) of this record",
          "type": "string"
        },
        "title": {
          "description": "Title of the e-book",
          "type": "string"
        },
        "description": {
          "description": "Description of the content and the usage limitations of the e-book",
          "type": "null"
        },
        "datetime": {
          "description": "The last time this record has been changed",
          "type": "integer"
        },
        "genre": {
          "description": "Genre of the e-book",
          "type": "string"
        },
        "author": {
          "description": "Author of the e-book. Several authors are separated by comma.",
          "type": "string"
        },
        "link": {
          "description": "URL to access the e-book.",
          "type": "string"
        }
      },
      "required": [
        "id",
        "title",
        "description",
        "datetime",
        "genre",
        "author",
        "link"
      ]
    },
    "success": {
      "description": "False if there was some error during the request, true otherwise. An empty result can also have success=true.",
      "type": "boolean"
    },
    "status": {
      "description": "HTTP status code returned from the knowledge base.",
      "type": "integer"
    }
  },
  "required": [
    "bookdata",
    "success",
    "status"
  ]
}